LICENSE
MANIFEST.in
README.md
setup.py
xmlarrangement_android.egg-info/PKG-INFO
xmlarrangement_android.egg-info/SOURCES.txt
xmlarrangement_android.egg-info/dependency_links.txt
xmlarrangement_android.egg-info/entry_points.txt
xmlarrangement_android.egg-info/top_level.txt
xmlarrangementandroid/__init__.py