Metadata-Version: 1.0
Name: xmlarrangement-android
Version: 0.1.1
Summary: XML Arrangement Rules Generator for Android CodeStyle
Home-page: https://github.com/jeanpimentel/xmlarrangement-android
Author: Jean Pimentel
Author-email: contato@jeanpimentel.com.br
License: UNKNOWN
Platform: UNKNOWN
